cocktail_apikit/__init__.py
cocktail_apikit/auth_kit.py
cocktail_apikit/aws_kit.py
cocktail_apikit/bottle_kit.py
cocktail_apikit/constants.py
cocktail_apikit/marshmallow_kit.py
cocktail_apikit/mongo_kit.py
cocktail_apikit/settings_kit.py
cocktail_apikit/utils_kit.py
cocktail_apikit-0.1.22.dist-info/LICENSE
cocktail_apikit-0.1.22.dist-info/METADATA
cocktail_apikit-0.1.22.dist-info/WHEEL
cocktail_apikit-0.1.22.dist-info/top_level.txt
cocktail_apikit-0.1.22.dist-info/RECORD
