Metadata-Version: 2.1
Name: cocktail-apikit
Version: 0.1.22
Summary: A collection of tools for APIs
Home-page: http://gitlab.com/theo-l/cocktail_apikit
Author: Liang Guisheng
Author-email: theol.liang@truckpad.com.br
License: MIT
Keywords: cocktail_apikit backend apikit
Platform: UNKNOWN
Classifier: Programming Language :: Python :: 3
Classifier: Intended Audience :: Developers
Classifier: License :: OSI Approved :: MIT License
Classifier: Operating System :: OS Independent
License-File: LICENSE
Requires-Dist: apispec[yaml] (<4)
Requires-Dist: apispec-webframeworks (==0.5.2)
Requires-Dist: asn1crypto (==1.4.0)
Requires-Dist: boto3 (==1.20.48)
Requires-Dist: bottle (==0.12.19)
Requires-Dist: certifi (==2019.3.9)
Requires-Dist: cffi (==1.15.0)
Requires-Dist: chardet (==4.0.0)
Requires-Dist: cryptography (==36.0.1)
Requires-Dist: docutils (==0.14)
Requires-Dist: idna (==2.8)
Requires-Dist: jmespath (==0.9.4)
Requires-Dist: marshmallow (~=2.16.3)
Requires-Dist: py (==1.10.0)
Requires-Dist: pycparser (==2.19)
Requires-Dist: pyjwt (==1.7.1)
Requires-Dist: pymongo[srv] (==3.11.4)
Requires-Dist: pyyaml (>=5.3.1)
Requires-Dist: requests (>=2.22.0)
Requires-Dist: s3transfer (>=0.3.0)
Requires-Dist: urllib3 (>=1.25.2)
Requires-Dist: python-dateutil (==2.8.0) ; python_version >= "2.7"
Provides-Extra: dev
Requires-Dist: atomicwrites (==1.3.0) ; extra == 'dev'
Requires-Dist: attrs (==19.2.0) ; extra == 'dev'
Requires-Dist: isort (==4.3.15) ; extra == 'dev'
Requires-Dist: lazy-object-proxy (==1.4.0) ; extra == 'dev'
Requires-Dist: more-itertools (==6.0.0) ; extra == 'dev'
Requires-Dist: pycodestyle (~=2.6.0) ; extra == 'dev'
Requires-Dist: pytest (>=7.0.0) ; extra == 'dev'
Requires-Dist: pytest-cov (>=2.10.1) ; extra == 'dev'
Requires-Dist: pylint (>=2.7.0) ; extra == 'dev'
Requires-Dist: rope (==0.12.0) ; extra == 'dev'
Requires-Dist: safety (>=1.10.3) ; extra == 'dev'
Requires-Dist: six (==1.12.0) ; extra == 'dev'
Requires-Dist: soupsieve (==1.8) ; extra == 'dev'
Requires-Dist: waitress (==1.4.4) ; extra == 'dev'
Requires-Dist: webob (==1.8.5) ; extra == 'dev'
Requires-Dist: webtest (==3.0.0) ; extra == 'dev'
Requires-Dist: wrapt (==1.11.1) ; extra == 'dev'
